{
    "backend": "api-server-nodejs",
    "db_name": "",
    "db_pass": "",
    "db_type": "sqlite",
    "db_user": "",
    "dbms": "1",
    "description": "generated product",
    "design": "berry-dashboard",
    "docker": "1",
    "err_code": 0,
    "frontend": "react",
    "heroku": "0",
    "pattern": "fullstack",
    "pro": "0",
    "task_id": "608abcaa-857a-428b-98c8-3ff5b6bda7ce",
    "task_info": "Upload Sources [0%] - 144 files",
    "task_output": "608abcaa-857a-428b-98c8-3ff5b6bda7ce.zip",
    "task_result": "SUCCESS",
    "task_state": "RUNNING",
    "task_ts_end": "2024-11-07-13-55-40",
    "task_ts_start": "2024-11-07-13-55-39"
}